README.md
acdb.py
setup.py
acdb.egg-info/PKG-INFO
acdb.egg-info/SOURCES.txt
acdb.egg-info/dependency_links.txt
acdb.egg-info/top_level.txt