Metadata-Version: 2.1
Name: acdb
Version: 3.7.3
Summary: Package acdb manages objects between memory and file system.
Home-page: https://github.com/pydump/acdb
Author: mohanson
Author-email: mohanson@outlook.com
License: MIT
Platform: UNKNOWN
